{
  "name": "DiskGraph",
  "directed": true,
  "strict": true,
  "nodesep": "0.35",
  "_subgraph_cnt": 2,
  "objects": [
    {
      "name": "cluster_graph",
      "color": "white",
      "nodesep": "0.35",
      "_gvid": 0,
      "subgraphs": [
        1
      ],
      "nodes": [
        2,3,4
      ],
      "edges": [
        0,1,2
      ]
    },
    {
      "name": "%9",
      "color": "white",
      "nodesep": "0.35",
      "rank": "same",
      "_gvid": 1,
      "nodes": [
        2,3,4
      ]
    },
    {
      "_gvid": 2,
      "name": "-4665722298727605580",
      "label": "x = \"ab\"",
      "style": "filled"
    },
    {
      "_gvid": 3,
      "name": "2400826549223885462",
      "label": "x = \"dklksjptykkgkg\"",
      "style": "filled"
    },
    {
      "_gvid": 4,
      "name": "740240026893633665",
      "label": "x = 9",
      "style": "filled"
    }
  ],
  "edges": [
    {
      "_gvid": 0,
      "tail": 2,
      "head": 2,
      "color": "black",
      "fontcolor": "black",
      "label": ""
    },
    {
      "_gvid": 1,
      "tail": 3,
      "head": 3,
      "color": "black",
      "fontcolor": "black",
      "label": ""
    },
    {
      "_gvid": 2,
      "tail": 4,
      "head": 4,
      "color": "black",
      "fontcolor": "black",
      "label": ""
    }
  ]
}
