{
  "states": [
    {
      "fp": 3283699574485891456,
      "val": {
        "x": 1,
        "y": 3
      }
    },
    {
      "fp": 379401839774704464,
      "val": {
        "x": 1,
        "y": 6
      }
    },
    {
      "fp": 5697847616264054809,
      "val": {
        "x": 2,
        "y": 3
      }
    },
    {
      "fp": 7476888646621737673,
      "val": {
        "x": 2,
        "y": 6
      }
    },
    {
      "fp": -5850117408709826315,
      "val": {
        "x": 209,
        "y": 288
      }
    }
  ],
  "edges": [
    [
      5697847616264054809,
      -5850117408709826315
    ],
    [
      7476888646621737673,
      -5850117408709826315
    ]
  ]
}